MANIFEST.in
readme.rst
requirements.txt
setup.py
tests.py
examples/filematch.py
howabout/__init__.py
howabout/version.py
howabout.egg-info/PKG-INFO
howabout.egg-info/SOURCES.txt
howabout.egg-info/dependency_links.txt
howabout.egg-info/requires.txt
howabout.egg-info/top_level.txt