Metadata-Version: 1.1
Name: howabout
Version: 1.1
Summary: A library to suggest similar strings.
Home-page: https://github.com/clibc/howabout
Author: Charlie Liban
Author-email: charlie@clib.ca
License: MIT License
Download-URL: https://github.com/clibc/howabout/zipball/master
Keywords: cli
Platform: UNKNOWN
Classifier: Programming Language :: Python
Classifier: License :: OSI Approved :: MIT License
